{
  "Product": [
    {

      "name": "sac 2",
      "reference": "445",
      "color": "red",
      "quantity": null,
      "phase": "production",
      "dimension": "",
      "marque": "a",

      "name": "hhh",
      "reference": "",
      "color": "",
      "quantity": null,
      "phase": "",
      "dimension": "",
      "marque": "",

      "type": "",
      "collection": "",
      "locallisation": "",
      "carton": "",

      "id": 2
    },
    {
      "name": "sac 2",
      "reference": "448",
      "color": "blue",
      "quantity": null,
      "phase": "prototype",
      "dimension": "",
      "marque": "b",

      "id": 1
    },
    {
      "name": "a",
      "reference": "5",
      "color": "",
      "quantity": null,
      "phase": "",
      "dimension": "",
      "marque": "",
      "type": "",
      "collection": "",
      "locallisation": "",
      "carton": "",
      "id": 2
    },
    {
      "name": "a",
      "reference": "4",
      "color": "",
      "quantity": null,
      "phase": "",
      "dimension": "",
      "marque": "",
      "type": "",
      "collection": "",
      "locallisation": "",
      "carton": "",
      "id": 3
    },
    {
      "name": "",
      "reference": "",
      "color": "",
      "quantity": null,
      "phase": "",
      "dimension": "",
      "marque": "",
      "type": "",
      "collection": "",
      "locallisation": "",
      "carton": "",
      "id": 4
    },
    {
      "name": "sac1",
      "reference": "1",
      "color": "blue",
      "quantity": null,
      "phase": "",
      "dimension": "",
      "marque": "",
      "type": "",
      "collection": "",
      "locallisation": "",
      "carton": "",
      "id": 5
    },
    {
      "name": "sac2",
      "reference": "1",
      "color": "green",
      "quantity": "1",
      "phase": "",
      "dimension": "",
      "marque": "",
      "type": "",
      "collection": "",
      "locallisation": "",
      "carton": "",
      "id": 6
    },
    {
      "name": "sac2",
      "reference": "25",
      "color": "green",
      "quantity": "1",
      "phase": "",
      "dimension": "",
      "marque": "",
      "type": "",
      "collection": "",
      "locallisation": "",
      "carton": "",
      "id": 7
    },
    {
      "name": "sac2",
      "reference": "25",
      "color": "blue",
      "quantity": "2",
      "phase": "",
      "dimension": "",
      "marque": "",

      "type": "",
      "collection": "",
      "locallisation": "",
      "carton": "",

      "id": 3
    },
    {
      "name": "sac3",
      "reference": "445",
      "color": "blue",

      "id": 8
    },
    {
      "name": "sac2",
      "reference": "5",
      "color": "red",
      "quantity": "3",
      "phase": "",
      "dimension": "",
      "marque": "",
      "type": "",
      "collection": "",
      "locallisation": "",
      "carton": "",
      "id": 9
    },
    {
      "name": "",
      "reference": "",
      "color": "",

      "quantity": null,
      "phase": "production",
      "dimension": "",

      "marque": "a",
      "type": "",
      "collection": "",
      "locallisation": "",
      "carton": "",
      "id": 4

      "marque": "",
      "type": "",
      "collection": "",
      "locallisation": "",
      "carton": "5",
      "id": 10

    }
  ],
  "history": [
    {
      "id": 1,
      "moderateur": "jon",
      "date": "05/05/2020",
      "action": "delete",
      "reference": "477"
    },
    {
      "id": 2,
      "moderateur": "molopp",
      "date": "05/05/2020",
      "action": "edit",
      "reference": "577"
    },
    {
      "id": 3,
      "moderateur": "kil",
      "date": "05/05/2020",
      "action": "add",
      "reference": "477"
    },
    {
      "id": 4,
      "moderateur": "kil",
      "date": "05/05/2020",
      "action": "add",
      "reference": "877"
    },
    {
      "name": "admin",
      "nameAction": "add Product",
      "date": "2020-06-24T21:57:00.962Z",
      "nameProduct": "",
      "id": 5
    },
    {
      "name": "admin",
      "nameAction": "add Product",
      "date": "2020-06-24T22:10:04.447Z",
      "nameProduct": "green",
      "id": 6
    },
    {
      "name": "admin",
      "nameAction": "add Product",
      "date": "2020-06-24T22:10:30.720Z",
      "nameProduct": "f",
      "id": 7
    },
    {
      "name": "admin",
      "nameAction": "add Product",
      "date": "2020-06-24T22:11:05.772Z",
      "nameProduct": "5",
      "id": 8
    },
    {
      "name": "admin",
      "nameAction": "add Product",
      "date": "2020-06-24T22:55:05.387Z",
      "nameProduct": "sac5",
      "id": 9
    },
    {
      "name": "admin",
      "nameAction": "delete product",
      "date": "2020-06-24T23:20:38.476Z",
      "nameProduct": "",
      "id": 10
    },
    {
      "name": "admin",
      "nameAction": "delete product",
      "date": "2020-06-24T23:20:41.227Z",
      "nameProduct": "",
      "id": 11
    },
    {
      "name": "admin",
      "nameAction": "edit Product",
      "date": "2020-06-25T00:12:33.048Z",
      "nameProduct": "q",
      "id": 12
    },
    {
      "name": "admin",
      "nameAction": "delete product",
      "date": "2020-06-25T08:08:45.862Z",
      "nameProduct": "",
      "id": 13
    },
    {
      "name": "admin",
      "nameAction": "add Product",
      "date": "2020-06-25T08:09:53.142Z",
      "nameProduct": "hhh",
      "id": 14
    },
    {
      "name": "admin",
      "nameAction": "add Product",

      "date": "2020-06-25T13:47:32.993Z",
      "nameProduct": "sac 2",

      "date": "2020-06-25T21:35:54.854Z",
      "nameProduct": "a",

      "id": 15
    },
    {
      "name": "admin",
      "nameAction": "add Product",

      "date": "2020-06-25T13:48:07.508Z",
      "nameProduct": "sac 2",

      "date": "2020-06-25T21:36:02.852Z",
      "nameProduct": "a",

      "id": 16
    },
    {
      "name": "admin",
      "nameAction": "add Product",

      "date": "2020-06-25T13:48:27.405Z",
      "nameProduct": "sac3",

      "date": "2020-06-25T22:09:05.624Z",
      "nameProduct": "",

      "id": 17
    },
    {
      "name": "admin",

      "nameAction": "delete product",
      "date": "2020-06-25T13:48:34.726Z",
      "nameProduct": "",
      "id": 18

      "nameAction": "add Product",
      "date": "2020-06-25T22:09:16.173Z",
      "nameProduct": "sac1",
      "id": 18
    },
    {
      "name": "admin",
      "nameAction": "add Product",
      "date": "2020-06-25T22:09:30.199Z",
      "nameProduct": "sac2",
      "id": 19
    },
    {
      "name": "admin",
      "nameAction": "add Product",
      "date": "2020-06-25T22:09:48.428Z",
      "nameProduct": "sac2",
      "id": 20
    },
    {
      "name": "admin",
      "nameAction": "add Product",
      "date": "2020-06-25T22:18:17.235Z",
      "nameProduct": "sac2 ",
      "id": 21
    },
    {
      "name": "admin",
      "nameAction": "edit Product",
      "date": "2020-06-25T22:36:58.724Z",
      "nameProduct": "",
      "id": 22
    },
    {
      "name": "admin",
      "nameAction": "edit Product",
      "date": "2020-06-25T22:37:18.136Z",
      "nameProduct": "",
      "id": 23
    },
    {
      "name": "admin",
      "nameAction": "delete product",
      "date": "2020-06-25T22:37:51.335Z",
      "nameProduct": "",
      "id": 24
    },
    {
      "name": "admin",
      "nameAction": "delete product",
      "date": "2020-06-25T22:37:53.064Z",
      "nameProduct": "",
      "id": 25
    },
    {
      "name": "admin",
      "nameAction": "delete product",
      "date": "2020-06-25T22:37:57.306Z",
      "nameProduct": "",
      "id": 26
    },
    {
      "name": "admin",
      "nameAction": "delete product",
      "date": "2020-06-25T22:37:59.913Z",
      "nameProduct": "",
      "id": 27
    },
    {
      "name": "admin",
      "nameAction": "delete product",
      "date": "2020-06-25T22:38:01.792Z",
      "nameProduct": "",
      "id": 28
    },
    {
      "name": "admin",
      "nameAction": "add Product",
      "date": "2020-06-25T22:38:16.230Z",
      "nameProduct": "sac2",
      "id": 29
    },
    {
      "name": "admin",
      "nameAction": "add Product",
      "date": "2020-06-25T22:38:51.490Z",
      "nameProduct": "sac2",
      "id": 30
    },
    {
      "name": "admin",
      "nameAction": "add Product",
      "date": "2020-06-25T22:39:06.456Z",
      "nameProduct": "sac2",
      "id": 31
    },
    {
      "name": "admin",
      "nameAction": "add Product",
      "date": "2020-06-25T22:39:21.441Z",
      "nameProduct": "sac2",
      "id": 32
    },
    {
      "name": "admin",
      "nameAction": "add Product",
      "date": "2020-06-25T23:29:16.928Z",
      "nameProduct": "",
      "id": 33

    }
  ],
  "users": [
    {
      "firstName": "admin",
      "lastName": "",
      "email": "takoua@gmail.com",
      "userName": "",
      "post": "",
      "password": "0000",
      "id": 1
    },
    {
      "id": 2,
      "firstName": "t",
      "password": "000",
      "email": "t@gmail.com",
      "role": "moderateur"
    },
    {
      "firstName": "tako",
      "lastName": "",
      "email": "a",
      "userName": "",
      "post": "",
      "password": "q",
      "id": 3
    },
    {
      "firstName": "oo",
      "lastName": "",
      "email": "b",
      "userName": "",
      "post": "",
      "password": "c",
      "id": 4
    }
  ],
  "session": {
    "id": 1,
    "role": "admin"
  },
  "userData": [
    {
      "firstName": "admin",
      "lastName": "",
      "email": "takoua@gmail.com",
      "userName": "",
      "post": "",
      "password": "0000",
      "id": 1
    }
  ]
}